reason_workbench/__init__.py
reason_workbench/main.py
reason_workbench-0.1.5.dist-info/METADATA
reason_workbench-0.1.5.dist-info/WHEEL
reason_workbench-0.1.5.dist-info/entry_points.txt
reason_workbench-0.1.5.dist-info/top_level.txt
reason_workbench-0.1.5.dist-info/RECORD
